pyUnfoldedCircleRemote/__init__.py
pyUnfoldedCircleRemote/const.py
pyUnfoldedCircleRemote/dock.py
pyUnfoldedCircleRemote/dock_websocket.py
pyUnfoldedCircleRemote/remote.py
pyUnfoldedCircleRemote/remote_websocket.py
pyUnfoldedCircleRemote/websocket.py
pyunfoldedcircleremote-0.15.6.dist-info/METADATA
pyunfoldedcircleremote-0.15.6.dist-info/WHEEL
pyunfoldedcircleremote-0.15.6.dist-info/licenses/LICENSE
pyunfoldedcircleremote-0.15.6.dist-info/RECORD
